lib/__init__.py
lib/thorne.py
thorne-0.0.1.dist-info/LICENSE
thorne-0.0.1.dist-info/METADATA
thorne-0.0.1.dist-info/WHEEL
thorne-0.0.1.dist-info/top_level.txt
thorne-0.0.1.dist-info/RECORD
