Metadata-Version: 2.1
Name: thorne
Version: 0.0.1
Summary: Thorne for Python
Home-page: https://github.com/ofsho/Thorne
Author: Cis International
Author-email: ofekbendavid9@gmail.com
License: UNKNOWN
Platform: UNKNOWN
Classifier: Programming Language :: Python :: 3
Classifier: License :: OSI Approved :: MIT License
Classifier: Operating System :: OS Independent
Requires-Python: >=3.5
